emailparser/__init__.py
emailparser/__main__.py
emailparser/cli.py
emailparser/parser.py
emailparser/pro_features.py
emailparserandsorting-0.1.3.dist-info/licenses/LICENSE
emailparserandsorting-0.1.3.dist-info/METADATA
emailparserandsorting-0.1.3.dist-info/WHEEL
emailparserandsorting-0.1.3.dist-info/entry_points.txt
emailparserandsorting-0.1.3.dist-info/top_level.txt
emailparserandsorting-0.1.3.dist-info/RECORD
