Metadata-Version: 2.4
Name: emailparserandsorting
Version: 0.1.3
Summary: A lightweight Python toolkit to parse .eml files and export to JSON, CSV, and more.
Home-page: https://github.com/coderreynolds/emailparser
Author: Royce Reynolds
Author-email: Royce Reynolds <jj.bird8900@gmail.com>
License: MIT
Project-URL: Homepage, https://github.com/coderreynolds/emailparser
Project-URL: BugTracker, https://github.com/coderreynolds/emailparser/issues
Project-URL: Source, https://github.com/coderreynolds/emailparser
Keywords: email,parser,eml,json,csv,cli
Classifier: Development Status :: 3 - Alpha
Classifier: Intended Audience :: Developers
Classifier: Topic :: Communications :: Email
Classifier: Topic :: Software Development :: Libraries :: Python Modules
Classifier: License :: OSI Approved :: MIT License
Classifier: Programming Language :: Python :: 3
Classifier: Programming Language :: Python :: 3.9
Classifier: Programming Language :: Python :: 3.10
Classifier: Programming Language :: Python :: 3.11
Classifier: Programming Language :: Python :: 3.12
Classifier: Programming Language :: Python :: 3.13
Requires-Python: >=3.9
License-File: LICENSE
Requires-Dist: mail-parser>=4.0.0
Provides-Extra: dev
Requires-Dist: pytest; extra == "dev"
Requires-Dist: pytest-cov; extra == "dev"
Requires-Dist: twine; extra == "dev"
Requires-Dist: build; extra == "dev"
Dynamic: author
Dynamic: home-page
Dynamic: license-file
Dynamic: requires-python
